[
  {
    "Route": "棕21",
    "SubRoute": "棕21經政大御花園",
    "Direction": 0,
    "Stops": [
      {
        "Name": "兆如安養中心",
        "Lat": 24.98942183,
        "Lon": 121.5843159,
        "Sequence": 1,
        "StationID": "5071"
      },
      {
        "Name": "普羅旺世",
        "Lat": 24.98776972,
        "Lon": 121.5838276,
        "Sequence": 2,
        "StationID": "5070"
      },
      {
        "Name": "政大三街",
        "Lat": 24.98603367,
        "Lon": 121.5828689,
        "Sequence": 3,
        "StationID": "1001383"
      },
      {
        "Name": "政大學苑",
        "Lat": 24.9852588957558,
        "Lon": 121.583528256631,
        "Sequence": 4,
        "StationID": "1165603215"
      },
      {
        "Name": "政大二街",
        "Lat": 24.985826,
        "Lon": 121.584378,
        "Sequence": 5,
        "StationID": "1165605316"
      },
      {
        "Name": "政大附中",
        "Lat": 24.98653114,
        "Lon": 121.5855192,
        "Sequence": 6,
        "StationID": "103"
      },
      {
        "Name": "棲霞山莊",
        "Lat": 24.98715168,
        "Lon": 121.5876992,
        "Sequence": 7,
        "StationID": "2472"
      },
      {
        "Name": "政大御花園",
        "Lat": 24.98565649,
        "Lon": 121.5872664,
        "Sequence": 8,
        "StationID": "2420"
      },
      {
        "Name": "政大御花園",
        "Lat": 24.98599992,
        "Lon": 121.5873303,
        "Sequence": 9,
        "StationID": "50679"
      },
      {
        "Name": "棲霞山莊",
        "Lat": 24.987239,
        "Lon": 121.587906,
        "Sequence": 10,
        "StationID": "50678"
      },
      {
        "Name": "綠野山莊",
        "Lat": 24.9881804824337,
        "Lon": 121.587632890382,
        "Sequence": 11,
        "StationID": "50677"
      },
      {
        "Name": "政大清境社區",
        "Lat": 24.98959656,
        "Lon": 121.5872624,
        "Sequence": 12,
        "StationID": "50676"
      },
      {
        "Name": "國關中心",
        "Lat": 24.98929,
        "Lon": 121.58023,
        "Sequence": 13,
        "StationID": "50675"
      },
      {
        "Name": "指南山莊",
        "Lat": 24.98905,
        "Lon": 121.57849,
        "Sequence": 14,
        "StationID": "2421"
      },
      {
        "Name": "萬興圖書館",
        "Lat": 24.989020423587586,
        "Lon": 121.57699279565435,
        "Sequence": 15,
        "StationID": "2520"
      },
      {
        "Name": "大誠高中",
        "Lat": 24.990413,
        "Lon": 121.576905,
        "Sequence": 16,
        "StationID": "2368"
      },
      {
        "Name": "萬壽橋頭(秀明)",
        "Lat": 24.991863,
        "Lon": 121.574627,
        "Sequence": 17,
        "StationID": "50671"
      },
      {
        "Name": "萬壽橋頭(新光)",
        "Lat": 24.992819,
        "Lon": 121.573853,
        "Sequence": 18,
        "StationID": "50669"
      },
      {
        "Name": "貓纜動物園站",
        "Lat": 24.9963006246947,
        "Lon": 121.576314002724,
        "Sequence": 19,
        "StationID": "2443"
      },
      {
        "Name": "捷運動物園站",
        "Lat": 24.99857,
        "Lon": 121.57996,
        "Sequence": 20,
        "StationID": "50672"
      },
      {
        "Name": "石壁坑",
        "Lat": 25.0028393386766,
        "Lon": 121.583287778248,
        "Sequence": 21,
        "StationID": "56111"
      },
      {
        "Name": "風動石",
        "Lat": 25.0011783104188,
        "Lon": 121.579255519338,
        "Sequence": 22,
        "StationID": "2429"
      },
      {
        "Name": "信義松仁路口(信義)",
        "Lat": 25.0329497897498,
        "Lon": 121.566687674056,
        "Sequence": 23,
        "StationID": "6929"
      },
      {
        "Name": "捷運台北101/世貿站(市府)",
        "Lat": 25.034512868313872,
        "Lon": 121.56357599974903,
        "Sequence": 24,
        "StationID": "2029"
      },
      {
        "Name": "市政府(市府)",
        "Lat": 25.038332,
        "Lon": 121.563754,
        "Sequence": 25,
        "StationID": "2063"
      },
      {
        "Name": "捷運市政府站",
        "Lat": 25.04100991,
        "Lon": 121.5668354,
        "Sequence": 26,
        "StationID": "3916"
      }
    ]
  },
  {
    "Route": "棕21",
    "SubRoute": "棕21經政大御花園",
    "Direction": 1,
    "Stops": [
      {
        "Name": "消防局(松仁)",
        "Lat": 25.038604,
        "Lon": 121.568284,
        "Sequence": 1,
        "StationID": "1165604593"
      },
      {
        "Name": "興雅國中",
        "Lat": 25.0372323905063,
        "Lon": 121.568268559011,
        "Sequence": 2,
        "StationID": "2179"
      },
      {
        "Name": "信義松仁路口(松仁)",
        "Lat": 25.0345352489599,
        "Lon": 121.568236043782,
        "Sequence": 3,
        "StationID": "2121"
      },
      {
        "Name": "風動石",
        "Lat": 25.00102,
        "Lon": 121.57937,
        "Sequence": 4,
        "StationID": "309"
      },
      {
        "Name": "石壁坑",
        "Lat": 25.00261,
        "Lon": 121.58301,
        "Sequence": 5,
        "StationID": "2400"
      },
      {
        "Name": "捷運動物園站",
        "Lat": 24.99881,
        "Lon": 121.58021,
        "Sequence": 6,
        "StationID": "2442"
      },
      {
        "Name": "貓纜動物園站",
        "Lat": 24.9968,
        "Lon": 121.576778,
        "Sequence": 7,
        "StationID": "1000436"
      },
      {
        "Name": "萬壽橋頭(新光)",
        "Lat": 24.993482,
        "Lon": 121.57363,
        "Sequence": 8,
        "StationID": "2512"
      },
      {
        "Name": "萬壽橋頭(秀明)",
        "Lat": 24.99161,
        "Lon": 121.574153,
        "Sequence": 9,
        "StationID": "2510"
      },
      {
        "Name": "萬興國小",
        "Lat": 24.989679,
        "Lon": 121.576757,
        "Sequence": 10,
        "StationID": "2519"
      },
      {
        "Name": "指南山莊",
        "Lat": 24.9889796040779,
        "Lon": 121.578601086333,
        "Sequence": 11,
        "StationID": "50674"
      },
      {
        "Name": "國關中心",
        "Lat": 24.98914141,
        "Lon": 121.5804463,
        "Sequence": 12,
        "StationID": "2438"
      },
      {
        "Name": "貓纜動物園南站",
        "Lat": 24.989841,
        "Lon": 121.586251,
        "Sequence": 13,
        "StationID": "4030"
      },
      {
        "Name": "政大清境社區",
        "Lat": 24.98948011,
        "Lon": 121.5874366,
        "Sequence": 14,
        "StationID": "2504"
      },
      {
        "Name": "綠野山莊",
        "Lat": 24.98829565,
        "Lon": 121.58742,
        "Sequence": 15,
        "StationID": "2526"
      },
      {
        "Name": "棲霞山莊",
        "Lat": 24.98715168,
        "Lon": 121.5876992,
        "Sequence": 16,
        "StationID": "2472"
      },
      {
        "Name": "政大御花園",
        "Lat": 24.98565649,
        "Lon": 121.5872664,
        "Sequence": 17,
        "StationID": "2420"
      },
      {
        "Name": "政大御花園",
        "Lat": 24.98599992,
        "Lon": 121.5873303,
        "Sequence": 18,
        "StationID": "50679"
      },
      {
        "Name": "棲霞山莊",
        "Lat": 24.9871695314337,
        "Lon": 121.587942169381,
        "Sequence": 19,
        "StationID": "50678"
      },
      {
        "Name": "政大附中",
        "Lat": 24.98695836,
        "Lon": 121.5857205,
        "Sequence": 20,
        "StationID": "50680"
      },
      {
        "Name": "政大二街",
        "Lat": 24.98614991,
        "Lon": 121.5846406,
        "Sequence": 21,
        "StationID": "1001387"
      },
      {
        "Name": "政大三街",
        "Lat": 24.98591151,
        "Lon": 121.5824604,
        "Sequence": 22,
        "StationID": "2417"
      },
      {
        "Name": "普羅旺世",
        "Lat": 24.98776697,
        "Lon": 121.5839587,
        "Sequence": 23,
        "StationID": "2471"
      },
      {
        "Name": "兆如安養中心",
        "Lat": 24.98942619,
        "Lon": 121.5844314,
        "Sequence": 24,
        "StationID": "2401"
      }
    ]
  },
  {
    "Route": "棕21",
    "SubRoute": "棕21不經政大御花園",
    "Direction": 0,
    "Stops": [
      {
        "Name": "政大一",
        "Lat": 24.98782160454249,
        "Lon": 121.57604615193513,
        "Sequence": 1,
        "StationID": "1001409"
      },
      {
        "Name": "政大(聯合醫院)",
        "Lat": 24.987374,
        "Lon": 121.576765,
        "Sequence": 2,
        "StationID": "1165604701"
      },
      {
        "Name": "小坑口(北政國中)",
        "Lat": 24.986195,
        "Lon": 121.579379,
        "Sequence": 3,
        "StationID": "2364"
      },
      {
        "Name": "政大學苑",
        "Lat": 24.9852588957558,
        "Lon": 121.583528256631,
        "Sequence": 4,
        "StationID": "1165603215"
      },
      {
        "Name": "政大二街",
        "Lat": 24.985826,
        "Lon": 121.584378,
        "Sequence": 5,
        "StationID": "1165605316"
      },
      {
        "Name": "政大附中",
        "Lat": 24.98653114,
        "Lon": 121.5855192,
        "Sequence": 6,
        "StationID": "103"
      },
      {
        "Name": "綠野山莊",
        "Lat": 24.9881804824337,
        "Lon": 121.587632890382,
        "Sequence": 7,
        "StationID": "50677"
      },
      {
        "Name": "政大清境社區",
        "Lat": 24.98959656,
        "Lon": 121.5872624,
        "Sequence": 8,
        "StationID": "50676"
      },
      {
        "Name": "國關中心",
        "Lat": 24.98929,
        "Lon": 121.58023,
        "Sequence": 9,
        "StationID": "50675"
      },
      {
        "Name": "指南山莊",
        "Lat": 24.98905,
        "Lon": 121.57849,
        "Sequence": 10,
        "StationID": "2421"
      },
      {
        "Name": "萬興圖書館",
        "Lat": 24.989020423587586,
        "Lon": 121.57699279565435,
        "Sequence": 11,
        "StationID": "2520"
      },
      {
        "Name": "大誠高中",
        "Lat": 24.990413,
        "Lon": 121.576905,
        "Sequence": 12,
        "StationID": "2368"
      },
      {
        "Name": "萬壽橋頭(秀明)",
        "Lat": 24.991863,
        "Lon": 121.574627,
        "Sequence": 13,
        "StationID": "50671"
      },
      {
        "Name": "萬壽橋頭(新光)",
        "Lat": 24.992819,
        "Lon": 121.573853,
        "Sequence": 14,
        "StationID": "50669"
      },
      {
        "Name": "貓纜動物園站",
        "Lat": 24.9963006246947,
        "Lon": 121.576314002724,
        "Sequence": 15,
        "StationID": "2443"
      },
      {
        "Name": "捷運動物園站",
        "Lat": 24.99857,
        "Lon": 121.57996,
        "Sequence": 16,
        "StationID": "50672"
      },
      {
        "Name": "石壁坑",
        "Lat": 25.0028393386766,
        "Lon": 121.583287778248,
        "Sequence": 17,
        "StationID": "56111"
      },
      {
        "Name": "風動石",
        "Lat": 25.0011783104188,
        "Lon": 121.579255519338,
        "Sequence": 18,
        "StationID": "2429"
      },
      {
        "Name": "信義松仁路口(信義)",
        "Lat": 25.0329497897498,
        "Lon": 121.566687674056,
        "Sequence": 19,
        "StationID": "6929"
      },
      {
        "Name": "捷運台北101/世貿站(市府)",
        "Lat": 25.034512868313872,
        "Lon": 121.56357599974903,
        "Sequence": 20,
        "StationID": "2029"
      },
      {
        "Name": "市政府(市府)",
        "Lat": 25.038332,
        "Lon": 121.563754,
        "Sequence": 21,
        "StationID": "2063"
      },
      {
        "Name": "捷運市政府站",
        "Lat": 25.04100991,
        "Lon": 121.5668354,
        "Sequence": 22,
        "StationID": "3916"
      }
    ]
  },
  {
    "Route": "棕21",
    "SubRoute": "棕21不經政大御花園",
    "Direction": 1,
    "Stops": [
      {
        "Name": "消防局(松仁)",
        "Lat": 25.038604,
        "Lon": 121.568284,
        "Sequence": 1,
        "StationID": "1165604593"
      },
      {
        "Name": "興雅國中",
        "Lat": 25.0372323905063,
        "Lon": 121.568268559011,
        "Sequence": 2,
        "StationID": "2179"
      },
      {
        "Name": "信義松仁路口(松仁)",
        "Lat": 25.0345352489599,
        "Lon": 121.568236043782,
        "Sequence": 3,
        "StationID": "2121"
      },
      {
        "Name": "風動石",
        "Lat": 25.00102,
        "Lon": 121.57937,
        "Sequence": 4,
        "StationID": "309"
      },
      {
        "Name": "石壁坑",
        "Lat": 25.00261,
        "Lon": 121.58301,
        "Sequence": 5,
        "StationID": "2400"
      },
      {
        "Name": "捷運動物園站",
        "Lat": 24.99881,
        "Lon": 121.58021,
        "Sequence": 6,
        "StationID": "2442"
      },
      {
        "Name": "貓纜動物園站",
        "Lat": 24.9968,
        "Lon": 121.576778,
        "Sequence": 7,
        "StationID": "1000436"
      },
      {
        "Name": "萬壽橋頭(新光)",
        "Lat": 24.993482,
        "Lon": 121.57363,
        "Sequence": 8,
        "StationID": "2512"
      },
      {
        "Name": "萬壽橋頭(秀明)",
        "Lat": 24.99161,
        "Lon": 121.574153,
        "Sequence": 9,
        "StationID": "2510"
      },
      {
        "Name": "萬興國小",
        "Lat": 24.989679,
        "Lon": 121.576757,
        "Sequence": 10,
        "StationID": "2519"
      },
      {
        "Name": "指南山莊",
        "Lat": 24.9889796040779,
        "Lon": 121.578601086333,
        "Sequence": 11,
        "StationID": "50674"
      },
      {
        "Name": "國關中心",
        "Lat": 24.98914141,
        "Lon": 121.5804463,
        "Sequence": 12,
        "StationID": "2438"
      },
      {
        "Name": "貓纜動物園南站",
        "Lat": 24.989841,
        "Lon": 121.586251,
        "Sequence": 13,
        "StationID": "4030"
      },
      {
        "Name": "政大清境社區",
        "Lat": 24.98948011,
        "Lon": 121.5874366,
        "Sequence": 14,
        "StationID": "2504"
      },
      {
        "Name": "綠野山莊",
        "Lat": 24.98829565,
        "Lon": 121.58742,
        "Sequence": 15,
        "StationID": "2526"
      },
      {
        "Name": "政大附中",
        "Lat": 24.98695836,
        "Lon": 121.5857205,
        "Sequence": 16,
        "StationID": "50680"
      },
      {
        "Name": "政大二街",
        "Lat": 24.98614991,
        "Lon": 121.5846406,
        "Sequence": 17,
        "StationID": "1001387"
      },
      {
        "Name": "政大和墅社區",
        "Lat": 24.98528376,
        "Lon": 121.5818292,
        "Sequence": 18,
        "StationID": "1001455"
      },
      {
        "Name": "小坑口(北政國中)",
        "Lat": 24.986063,
        "Lon": 121.579711,
        "Sequence": 19,
        "StationID": "56088"
      },
      {
        "Name": "政大",
        "Lat": 24.987567,
        "Lon": 121.576536,
        "Sequence": 20,
        "StationID": "3988"
      }
    ]
  }
]